ecalic/__init__.py
ecalic/cmsStyle.py
ecalic/ic.py
ecalic/iov.py
ecalic/data/ecalMapping.txt
ecalic/data/ecalMapping.v1.0.0.txt
ecalic/data/fStyle.mplstyle
ecalic-1.0.5.dist-info/licenses/LICENSE
ecalic-1.0.5.dist-info/METADATA
ecalic-1.0.5.dist-info/WHEEL
ecalic-1.0.5.dist-info/top_level.txt
ecalic-1.0.5.dist-info/RECORD
