Metadata-Version: 2.4
Name: ecalic
Version: 1.0.5
Summary: A package to handle CMS Ecal InterCalibration constants and Ecal geometry
Home-page: https://gitlab.cern.ch/cms-ecal-dpg/ecalic
Author: Fabrice Couderc
Author-email: fabrice.couderc@cern.ch
Classifier: Programming Language :: Python
Classifier: License :: OSI Approved :: GNU General Public License v3 (GPLv3)
Classifier: Operating System :: OS Independent
Requires-Python: >=3.6
License-File: LICENSE
Requires-Dist: matplotlib
Requires-Dist: pandas
Requires-Dist: lxml
Requires-Dist: numpy
Dynamic: author
Dynamic: author-email
Dynamic: classifier
Dynamic: description
Dynamic: description-content-type
Dynamic: home-page
Dynamic: license-file
Dynamic: requires-dist
Dynamic: requires-python
Dynamic: summary
